splmeter/__init__.py
splmeter/base.py
splmeter/signal.py
splmeter/visualizer.py
splmeter/measure/__init__.py
splmeter/measure/frequency.py
splmeter/measure/time.py
splmeter/processing/__init__.py
splmeter/processing/frequency.py
splmeter/processing/time.py
splmeter-0.0.8.dist-info/LICENSE
splmeter-0.0.8.dist-info/METADATA
splmeter-0.0.8.dist-info/WHEEL
splmeter-0.0.8.dist-info/top_level.txt
splmeter-0.0.8.dist-info/RECORD
