Metadata-Version: 2.1
Name: splmeter
Version: 0.0.8
Summary: SPLMeter
Author-email: Sumeet <s.saini@ufl.edu>
Project-URL: Homepage, https://github.com/Sumeet2807/splmeter
Project-URL: Bug Tracker, https://github.com/Sumeet2807/splmeter/issues
Classifier: Programming Language :: Python :: 3
Classifier: License :: OSI Approved :: MIT License
Classifier: Operating System :: OS Independent
Requires-Python: >=3.7
License-File: LICENSE
Requires-Dist: numpy
Requires-Dist: plotly
Requires-Dist: schemdraw
Requires-Dist: scipy
